routertracer/__init__.py
routertracer-1.dist-info/License
routertracer-1.dist-info/METADATA
routertracer-1.dist-info/WHEEL
routertracer-1.dist-info/top_level.txt
routertracer-1.dist-info/RECORD
