Metadata-Version: 2.1
Name: routertracer
Version: 1
Summary: Output traceroute hops 'ip, rtt, AS number, and service provider' into a json file
Home-page: https://github.com/klauswong123/routertracert
Author: klauswong123
Author-email: klauswangjinpeng@gmail.com
License: UNKNOWN
Platform: UNKNOWN
Classifier: Programming Language :: Python :: 3
Classifier: License :: OSI Approved :: MIT License
Classifier: Operating System :: OS Independent
Requires-Python: >=3.6
